moyopy-0.7.4.dist-info/METADATA
moyopy-0.7.4.dist-info/WHEEL
moyopy/__init__.py
moyopy/_base.pyi
moyopy/_data.pyi
moyopy/_dataset.pyi
moyopy/_identify.pyi
moyopy/_moyopy.abi3.so
moyopy/_moyopy.pyi
moyopy/interface.py
moyopy/py.typed
moyopy-0.7.4.dist-info/RECORD
